sqlalchemy/__init__.py
sqlalchemy/events.py
sqlalchemy/exc.py
sqlalchemy/inspection.py
sqlalchemy/log.py
sqlalchemy/py.typed
sqlalchemy/schema.py
sqlalchemy/types.py
sqlalchemy/connectors/__init__.py
sqlalchemy/connectors/pyodbc.py
sqlalchemy/cyextension/__init__.py
sqlalchemy/cyextension/collections.cpython-311-darwin.so
sqlalchemy/cyextension/collections.pyx
sqlalchemy/cyextension/immutabledict.cpython-311-darwin.so
sqlalchemy/cyextension/immutabledict.pxd
sqlalchemy/cyextension/immutabledict.pyx
sqlalchemy/cyextension/processors.cpython-311-darwin.so
sqlalchemy/cyextension/processors.pyx
sqlalchemy/cyextension/resultproxy.cpython-311-darwin.so
sqlalchemy/cyextension/resultproxy.pyx
sqlalchemy/cyextension/util.cpython-311-darwin.so
sqlalchemy/cyextension/util.pyx
sqlalchemy/dialects/__init__.py
sqlalchemy/dialects/type_migration_guidelines.txt
sqlalchemy/dialects/mssql/__init__.py
sqlalchemy/dialects/mssql/base.py
sqlalchemy/dialects/mssql/information_schema.py
sqlalchemy/dialects/mssql/json.py
sqlalchemy/dialects/mssql/provision.py
sqlalchemy/dialects/mssql/pymssql.py
sqlalchemy/dialects/mssql/pyodbc.py
sqlalchemy/dialects/mysql/__init__.py
sqlalchemy/dialects/mysql/aiomysql.py
sqlalchemy/dialects/mysql/asyncmy.py
sqlalchemy/dialects/mysql/base.py
sqlalchemy/dialects/mysql/cymysql.py
sqlalchemy/dialects/mysql/dml.py
sqlalchemy/dialects/mysql/enumerated.py
sqlalchemy/dialects/mysql/expression.py
sqlalchemy/dialects/mysql/json.py
sqlalchemy/dialects/mysql/mariadb.py
sqlalchemy/dialects/mysql/mariadbconnector.py
sqlalchemy/dialects/mysql/mysqlconnector.py
sqlalchemy/dialects/mysql/mysqldb.py
sqlalchemy/dialects/mysql/provision.py
sqlalchemy/dialects/mysql/pymysql.py
sqlalchemy/dialects/mysql/pyodbc.py
sqlalchemy/dialects/mysql/reflection.py
sqlalchemy/dialects/mysql/reserved_words.py
sqlalchemy/dialects/mysql/types.py
sqlalchemy/dialects/oracle/__init__.py
sqlalchemy/dialects/oracle/base.py
sqlalchemy/dialects/oracle/cx_oracle.py
sqlalchemy_patch-2.0.15.dev0.dist-info/LICENSE
sqlalchemy_patch-2.0.15.dev0.dist-info/METADATA
sqlalchemy_patch-2.0.15.dev0.dist-info/WHEEL
sqlalchemy_patch-2.0.15.dev0.dist-info/top_level.txt
sqlalchemy_patch-2.0.15.dev0.dist-info/RECORD
